Metadata-Version: 2.1
Name: lyytaode
Version: 1.1
Summary: lyytaode for lyy
Author: td
Author-email: 
License: MIT
License-File: LICENSE
